dash2html/__init__.py
dash2html/utils.py
dash2html-1.0.2.dist-info/METADATA
dash2html-1.0.2.dist-info/WHEEL
dash2html-1.0.2.dist-info/top_level.txt
dash2html-1.0.2.dist-info/RECORD
