Metadata-Version: 2.1
Name: dash2html
Version: 1.0.2
Summary: Convert Plotly Dash App To Static HTML File
Author: Jenil sheth
Author-email: shethjeniljigneshbhai@gmail.com
Requires-Dist: flask
Requires-Dist: dash
Requires-Dist: requests
